MANIFEST.in
dev-requirements.txt
dist_utils.py
requirements.txt
setup.py
circleci_helpers/__init__.py
circleci_helpers/errors.py
circleci_helpers/logger.py
circleci_helpers/shellhelpers.py
circleci_helpers.egg-info/PKG-INFO
circleci_helpers.egg-info/SOURCES.txt
circleci_helpers.egg-info/dependency_links.txt
circleci_helpers.egg-info/entry_points.txt
circleci_helpers.egg-info/requires.txt
circleci_helpers.egg-info/top_level.txt
circleci_helpers/matrix/__init__.py
circleci_helpers/matrix/cli.py
circleci_helpers/matrix/config.py
circleci_helpers/matrix/main.py
circleci_helpers/matrix/matrix.py
circleci_helpers/matrix/runner.py
circleci_helpers/matrix/schema.yml