Metadata-Version: 1.0
Name: circleci-helpers
Version: 0.1.1
Summary: Provides useful helpers for Circle CI
Home-page: https://github.com/dennybaa/circleci-helpers
Author: Denis Baryshev
Author-email: dennybaa@gmail.com
License: MIT
Platform: UNKNOWN
